{
    "stt": 1824,
    "msmh": "MA2001",
    "monhoc": "Vật lý chất rắn",
    "course": "Solid State Physics",
    "dieukiendangky": "MA1003(SH) PH1003(HT)",
    "tinchi": 2,
    "ecth": 4,
    "pbstc_lt": 2,
    "pbstc_thl_th": 0,
    "pbstc_tn": 0,
    "pbstc_thq": 0,
    "pbstc_da": 0,
    "pbstc_ttnt": 0,
    "pbstc_lvtn": 0,
    "sotiet": 30,
    "pbst_lt": 30,
    "pbst_thl_th": 0,
    "pbst_tn": 0,
    "pbst_thq": 0,
    "pbst_da": 0,
    "pbst_ttnt": 0,
    "pbst_lvtn": 0,
    "tldgpt_thl_th": 15,
    "tldgpt_tn": "",
    "tldgpt_th": "",
    "tldgpt_da": 20,
    "tldgpt_kt": 25,
    "tldgpt_thi": 40,
    "kt_hinhthuc": "Trắc nghiệm (TN),Tự luận",
    "kt_sophut": 50,
    "thi_hinhthuc": "Trắc nghiệm (TN),Tự luận",
    "thi_sophut": 50,
    "bomonphutrach": "Giáo Vụ Khoa CN Vật Liệu",
    "mau": "",
    "khoa": "VL"
}